{
    "__comment": "Model generated using MrCrayfish's Model Creator (http://mrcrayfish.com/modelcreator/)",
"ambientocclusion": false,
    "textures": {
        "0": "blocks/anvil_base",
        "1": "blocks/torch_on",
        "2": "blocks/glass"
    },
    "elements": [
        {
            "name": "north bottom",
            "from": [ 4.0, 1.0, 3.0 ], 
            "to": [ 12.0, 5.0, 4.0 ], 
            "faces": {
                "north": { "texture": "#0", "uv": [ 0.0, 0.0, 8.0, 4.0 ] },
                "east": { "texture": "#0", "uv": [ 0.0, 0.0, 1.0, 4.0 ] },
                "south": { "texture": "#0", "uv": [ 0.0, 0.0, 8.0, 4.0 ] },
                "west": { "texture": "#0", "uv": [ 0.0, 0.0, 1.0, 4.0 ] },
                "up": { "texture": "#0", "uv": [ 0.0, 0.0, 8.0, 1.0 ] },
                "down": { "texture": "#0", "uv": [ 0.0, 0.0, 8.0, 1.0 ] }
            }
        },
        {
            "name": "south bottom",
            "from": [ 4.0, 1.0, 12.0 ], 
            "to": [ 12.0, 5.0, 13.0 ], 
            "faces": {
                "north": { "texture": "#0", "uv": [ 0.0, 0.0, 8.0, 4.0 ] },
                "east": { "texture": "#0", "uv": [ 0.0, 0.0, 1.0, 4.0 ] },
                "south": { "texture": "#0", "uv": [ 0.0, 0.0, 8.0, 4.0 ] },
                "west": { "texture": "#0", "uv": [ 0.0, 0.0, 1.0, 4.0 ] },
                "up": { "texture": "#0", "uv": [ 0.0, 0.0, 8.0, 1.0 ] },
                "down": { "texture": "#0", "uv": [ 0.0, 0.0, 8.0, 1.0 ] }
            }
        },
        {
            "name": "west bottom",
            "from": [ 3.0, 1.0, 4.0 ], 
            "to": [ 4.0, 5.0, 12.0 ], 
            "faces": {
                "north": { "texture": "#0", "uv": [ 0.0, 0.0, 1.0, 4.0 ] },
                "east": { "texture": "#0", "uv": [ 0.0, 0.0, 8.0, 4.0 ] },
                "south": { "texture": "#0", "uv": [ 0.0, 0.0, 1.0, 4.0 ] },
                "west": { "texture": "#0", "uv": [ 0.0, 0.0, 8.0, 4.0 ] },
                "up": { "texture": "#0", "uv": [ 0.0, 0.0, 1.0, 8.0 ] },
                "down": { "texture": "#0", "uv": [ 0.0, 0.0, 1.0, 8.0 ] }
            }
        },
        {
            "name": "east bottom",
            "from": [ 12.0, 1.0, 4.0 ], 
            "to": [ 13.0, 5.0, 12.0 ], 
            "faces": {
                "north": { "texture": "#0", "uv": [ 0.0, 0.0, 1.0, 4.0 ] },
                "east": { "texture": "#0", "uv": [ 0.0, 0.0, 8.0, 4.0 ] },
                "south": { "texture": "#0", "uv": [ 0.0, 0.0, 1.0, 4.0 ] },
                "west": { "texture": "#0", "uv": [ 0.0, 0.0, 8.0, 4.0 ] },
                "up": { "texture": "#0", "uv": [ 0.0, 0.0, 1.0, 8.0 ] },
                "down": { "texture": "#0", "uv": [ 0.0, 0.0, 1.0, 8.0 ] }
            }
        },
        {
            "name": "Bottom",
            "from": [ 4.0, 0.0, 4.0 ], 
            "to": [ 12.0, 1.0, 12.0 ], 
            "faces": {
                "north": { "texture": "#0", "uv": [ 0.0, 0.0, 8.0, 1.0 ] },
                "east": { "texture": "#0", "uv": [ 0.0, 0.0, 8.0, 1.0 ] },
                "south": { "texture": "#0", "uv": [ 0.0, 0.0, 8.0, 1.0 ] },
                "west": { "texture": "#0", "uv": [ 0.0, 0.0, 8.0, 1.0 ] },
                "up": { "texture": "#0", "uv": [ 0.0, 0.0, 8.0, 8.0 ] },
                "down": { "texture": "#0", "uv": [ 0.0, 0.0, 8.0, 8.0 ] }
            }
        },
        {
            "name": "torch",
            "from": [ 7.5, 3.0, 7.5 ], 
            "to": [ 8.5, 9.0, 8.5 ], 
            "faces": {
                "north": { "texture": "#1", "uv": [ 7.0, 6.0, 9.0, 16.0 ] },
                "east": { "texture": "#1", "uv": [ 7.0, 6.0, 9.0, 16.0 ] },
                "south": { "texture": "#1", "uv": [ 7.0, 6.0, 9.0, 16.0 ] },
                "west": { "texture": "#1", "uv": [ 7.0, 6.0, 9.0, 16.0 ] },
                "up": { "texture": "#1", "uv": [ 7.0, 6.0, 9.0, 16.0 ] },
                "down": { "texture": "#1", "uv": [ 7.0, 6.0, 9.0, 16.0 ] }
            }
        },
        {
            "name": "glass right",
            "from": [ 11.0, 3.0, 5.0 ], 
            "to": [ 12.0, 11.0, 11.0 ], 
            "faces": {
                "north": { "texture": "#2", "uv": [ 0.0, 0.0, 16.0, 16.0 ] },
                "east": { "texture": "#2", "uv": [ 0.0, 0.0, 16.0, 16.0 ] },
                "south": { "texture": "#2", "uv": [ 0.0, 0.0, 16.0, 16.0 ] },
                "west": { "texture": "#2", "uv": [ 0.0, 0.0, 16.0, 16.0 ] },
                "up": { "texture": "#2", "uv": [ 0.0, 0.0, 13.0, 15.0 ] },
                "down": { "texture": "#2", "uv": [ 0.0, 0.0, 16.0, 16.0 ] }
            }
        },
        {
            "name": "glass back",
            "from": [ 5.0, 3.0, 4.0 ], 
            "to": [ 11.0, 11.0, 5.0 ], 
            "faces": {
                "north": { "texture": "#2", "uv": [ 0.0, 0.0, 16.0, 16.0 ] },
                "east": { "texture": "#2", "uv": [ 0.0, 0.0, 16.0, 16.0 ] },
                "south": { "texture": "#2", "uv": [ 0.0, 0.0, 16.0, 16.0 ] },
                "west": { "texture": "#2", "uv": [ 0.0, 0.0, 16.0, 16.0 ] },
                "up": { "texture": "#2", "uv": [ 0.0, 0.0, 13.0, 15.0 ] },
                "down": { "texture": "#2", "uv": [ 0.0, 0.0, 16.0, 16.0 ] }
            }
        },
        {
            "name": "glass front",
            "from": [ 5.0, 3.0, 11.0 ], 
            "to": [ 11.0, 11.0, 12.0 ], 
            "faces": {
                "north": { "texture": "#2", "uv": [ 0.0, 0.0, 16.0, 16.0 ] },
                "east": { "texture": "#2", "uv": [ 0.0, 0.0, 16.0, 16.0 ] },
                "south": { "texture": "#2", "uv": [ 0.0, 0.0, 16.0, 16.0 ] },
                "west": { "texture": "#2", "uv": [ 0.0, 0.0, 16.0, 16.0 ] },
                "up": { "texture": "#2", "uv": [ 0.0, 0.0, 13.0, 15.0 ] },
                "down": { "texture": "#2", "uv": [ 0.0, 0.0, 16.0, 16.0 ] }
            }
        },
        {
            "name": "glass left",
            "from": [ 4.0, 3.0, 5.0 ], 
            "to": [ 5.0, 11.0, 11.0 ], 
            "faces": {
                "north": { "texture": "#2", "uv": [ 0.0, 0.0, 16.0, 16.0 ] },
                "east": { "texture": "#2", "uv": [ 0.0, 0.0, 16.0, 16.0 ] },
                "south": { "texture": "#2", "uv": [ 0.0, 0.0, 16.0, 16.0 ] },
                "west": { "texture": "#2", "uv": [ 0.0, 0.0, 16.0, 16.0 ] },
                "up": { "texture": "#2", "uv": [ 0.0, 0.0, 13.0, 15.0 ] },
                "down": { "texture": "#2", "uv": [ 0.0, 0.0, 16.0, 16.0 ] }
            }
        },
        {
            "name": "Cube",
            "from": [ 5.0, 11.0, 4.0 ], 
            "to": [ 11.0, 14.0, 5.0 ], 
            "faces": {
                "north": { "texture": "#0", "uv": [ 0.0, 0.0, 6.0, 3.0 ] },
                "east": { "texture": "#0", "uv": [ 0.0, 0.0, 1.0, 3.0 ] },
                "south": { "texture": "#0", "uv": [ 0.0, 0.0, 6.0, 3.0 ] },
                "west": { "texture": "#0", "uv": [ 0.0, 0.0, 1.0, 3.0 ] },
                "up": { "texture": "#0", "uv": [ 0.0, 0.0, 6.0, 1.0 ] },
                "down": { "texture": "#0", "uv": [ 0.0, 0.0, 6.0, 1.0 ] }
            }
        },
        {
            "name": "Cube",
            "from": [ 5.0, 11.0, 11.0 ], 
            "to": [ 11.0, 14.0, 12.0 ], 
            "faces": {
                "north": { "texture": "#0", "uv": [ 0.0, 0.0, 6.0, 3.0 ] },
                "east": { "texture": "#0", "uv": [ 0.0, 0.0, 1.0, 3.0 ] },
                "south": { "texture": "#0", "uv": [ 0.0, 0.0, 6.0, 3.0 ] },
                "west": { "texture": "#0", "uv": [ 0.0, 0.0, 1.0, 3.0 ] },
                "up": { "texture": "#0", "uv": [ 0.0, 0.0, 6.0, 1.0 ] },
                "down": { "texture": "#0", "uv": [ 0.0, 0.0, 6.0, 1.0 ] }
            }
        },
        {
            "name": "Cube",
            "from": [ 4.0, 11.0, 5.0 ], 
            "to": [ 5.0, 14.0, 11.0 ], 
            "faces": {
                "north": { "texture": "#0", "uv": [ 0.0, 0.0, 1.0, 3.0 ] },
                "east": { "texture": "#0", "uv": [ 0.0, 0.0, 6.0, 3.0 ] },
                "south": { "texture": "#0", "uv": [ 0.0, 0.0, 1.0, 3.0 ] },
                "west": { "texture": "#0", "uv": [ 0.0, 0.0, 6.0, 3.0 ] },
                "up": { "texture": "#0", "uv": [ 0.0, 0.0, 1.0, 6.0 ] },
                "down": { "texture": "#0", "uv": [ 0.0, 0.0, 1.0, 6.0 ] }
            }
        },
        {
            "name": "Cube",
            "from": [ 11.0, 11.0, 5.0 ], 
            "to": [ 12.0, 14.0, 11.0 ], 
            "faces": {
                "north": { "texture": "#0", "uv": [ 0.0, 0.0, 1.0, 3.0 ] },
                "east": { "texture": "#0", "uv": [ 0.0, 0.0, 6.0, 3.0 ] },
                "south": { "texture": "#0", "uv": [ 0.0, 0.0, 1.0, 3.0 ] },
                "west": { "texture": "#0", "uv": [ 0.0, 0.0, 6.0, 3.0 ] },
                "up": { "texture": "#0", "uv": [ 0.0, 0.0, 1.0, 6.0 ] },
                "down": { "texture": "#0", "uv": [ 0.0, 0.0, 1.0, 6.0 ] }
            }
        },
        {
            "name": "Cube",
            "from": [ 5.0, 14.0, 5.0 ], 
            "to": [ 11.0, 15.0, 11.0 ], 
            "faces": {
                "north": { "texture": "#0", "uv": [ 0.0, 0.0, 6.0, 1.0 ] },
                "east": { "texture": "#0", "uv": [ 0.0, 0.0, 6.0, 1.0 ] },
                "south": { "texture": "#0", "uv": [ 0.0, 0.0, 6.0, 1.0 ] },
                "west": { "texture": "#0", "uv": [ 0.0, 0.0, 6.0, 1.0 ] },
                "up": { "texture": "#0", "uv": [ 0.0, 0.0, 6.0, 6.0 ] },
                "down": { "texture": "#0", "uv": [ 0.0, 0.0, 6.0, 6.0 ] }
            }
        },
        {
            "name": "Cube",
            "from": [ 0.0, 6.0, 7.5 ], 
            "to": [ 4.0, 7.0, 8.5 ], 
            "faces": {
                "north": { "texture": "#0", "uv": [ 0.0, 0.0, 4.0, 1.0 ] },
                "east": { "texture": "#0", "uv": [ 0.0, 0.0, 1.0, 1.0 ] },
                "south": { "texture": "#0", "uv": [ 0.0, 0.0, 4.0, 1.0 ] },
                "west": { "texture": "#0", "uv": [ 0.0, 0.0, 1.0, 1.0 ] },
                "up": { "texture": "#0", "uv": [ 0.0, 0.0, 4.0, 1.0 ] },
                "down": { "texture": "#0", "uv": [ 0.0, 0.0, 4.0, 1.0 ] }
            }
        },
        {
            "name": "Cube",
            "from": [ 0.0, 10.0, 7.5 ], 
            "to": [ 4.0, 11.0, 8.5 ], 
            "faces": {
                "north": { "texture": "#0", "uv": [ 0.0, 0.0, 4.0, 1.0 ] },
                "east": { "texture": "#0", "uv": [ 0.0, 0.0, 1.0, 1.0 ] },
                "south": { "texture": "#0", "uv": [ 0.0, 0.0, 4.0, 1.0 ] },
                "west": { "texture": "#0", "uv": [ 0.0, 0.0, 1.0, 1.0 ] },
                "up": { "texture": "#0", "uv": [ 0.0, 0.0, 4.0, 1.0 ] },
                "down": { "texture": "#0", "uv": [ 0.0, 0.0, 4.0, 1.0 ] }
            }
        },
        {
            "name": "Cube",
            "from": [ 0.0, 7.0, 7.5 ], 
            "to": [ 1.0, 11.0, 8.5 ], 
            "faces": {
                "north": { "texture": "#0", "uv": [ 0.0, 0.0, 1.0, 4.0 ] },
                "east": { "texture": "#0", "uv": [ 0.0, 0.0, 1.0, 4.0 ] },
                "south": { "texture": "#0", "uv": [ 0.0, 0.0, 1.0, 4.0 ] },
                "west": { "texture": "#0", "uv": [ 0.0, 0.0, 1.0, 4.0 ] },
                "up": { "texture": "#0", "uv": [ 0.0, 0.0, 1.0, 1.0 ] },
                "down": { "texture": "#0", "uv": [ 0.0, 0.0, 1.0, 1.0 ] }
            }
        }
    ]
}